{
    "type": "FeatureCollection",
    "features": [
        {
            "type": "Feature",
            "id": 0,
            "geometry": {
                "type": "Polygon",
                "coordinates": [
                    [
                        [
                            -93.5,
                            30.0
                        ],
                        [
                            -93.5,
                            30.5
                        ],
                        [
                            -93.0,
                            30.5
                        ],
                        [
                            -93.0,
                            30.0
                        ],
                        [
                            -93.5,
                            30.0
                        ]
                    ]
                ]
            },
            "properties": {
                "FID": 0,
                "Id": 0,
                "map-link-tiff": "GeoIntelX/Images/Figures/2Z1ag6DogqP1LgvqbrDZQjeX_Fig.png"
            }
        }
    ]
}